pyredux/__init__.py
pyredux/actions.py
pyredux/middleware.py
pyredux/reducer.py
pyredux/static_data.py
pyredux/store.py
pyredux/utils.py
pyredux-1.0.1.dist-info/DESCRIPTION.rst
pyredux-1.0.1.dist-info/METADATA
pyredux-1.0.1.dist-info/RECORD
pyredux-1.0.1.dist-info/WHEEL
pyredux-1.0.1.dist-info/metadata.json
pyredux-1.0.1.dist-info/top_level.txt
